pydubbo/__init__.py
pydubbo/pydubbo.py
pydubbo-0.1.1.dist-info/METADATA
pydubbo-0.1.1.dist-info/RECORD
pydubbo-0.1.1.dist-info/WHEEL
pydubbo-0.1.1.dist-info/top_level.txt
utils/__init__.py
utils/encoder.py
utils/parser.py
