Metadata-Version: 2.1
Name: pydubbo
Version: 0.1.1
Summary: python调用dubbo,目前支持dubbo协议，不需要服务端修改成jsonrpc.实现客户端的负载均衡、配合Zookeeper自动发现服务功能等
Home-page: https://github.com/morningzhang/dubbo
Author: zhangliming
Author-email: 149151874@qq.com
Maintainer: zhangliming
Maintainer-email: 149151874@qq.com
License: BSD License
Platform: all
Classifier: Development Status :: 4 - Beta
Classifier: Operating System :: OS Independent
Classifier: Intended Audience :: Developers
Classifier: License :: OSI Approved :: BSD License
Classifier: Programming Language :: Python
Classifier: Programming Language :: Python :: Implementation
Classifier: Programming Language :: Python :: 2
Classifier: Programming Language :: Python :: 2.7
Classifier: Programming Language :: Python :: 3
Classifier: Programming Language :: Python :: 3.4
Classifier: Programming Language :: Python :: 3.5
Classifier: Programming Language :: Python :: 3.6
Classifier: Topic :: Software Development :: Libraries
Requires-Dist: kazoo (>=2.5.0)
Requires-Dist: bitstring (>=3.1.5)
Requires-Dist: python-hessian (>=1.0.2)
